CHANGELOG.md
LICENSE
gl_search/__init__.py
gl_search/__main__.py
gl_search/cli.py
gl_search/clis/__init__.py
gl_search/clis/config.py
gl_search/clis/search.py
gl_search/config.py
gl_search/display.py
gl_search/models.py
gl_search/search.py
gl_search/utils.py
gl_search-0.4.1.dist-info/LICENSE
gl_search-0.4.1.dist-info/METADATA
gl_search-0.4.1.dist-info/WHEEL
gl_search-0.4.1.dist-info/entry_points.txt
gl_search-0.4.1.dist-info/RECORD
