Metadata-Version: 2.1
Name: gl_search
Version: 0.4.1
Summary: Script to help search code in self-hosted gitlab
Home-page: https://github.com/Bernardoow/gl_search
License: MIT
Keywords: gitlab,search,search code,api
Author: Bernardo Gomes
Author-email: bgomesdeabreu@gmail.com
Maintainer: Bernardo Gomes
Maintainer-email: bgomesdeabreu@gmail.com
Requires-Python: >=3.9,<4.0
Classifier: Environment :: Console
Classifier: License :: OSI Approved :: MIT License
Classifier: Programming Language :: Python
Classifier: Programming Language :: Python :: 3
Classifier: Programming Language :: Python :: 3.9
Classifier: Programming Language :: Python :: 3.10
Classifier: Programming Language :: Python :: 3.11
Classifier: Programming Language :: Python :: 3.12
Classifier: Topic :: Terminals
Classifier: Topic :: Utilities
Requires-Dist: click (>=8.1.3)
Requires-Dist: dynaconf (>=3.1.11)
Requires-Dist: pydantic (>=1.10.2,<2.0.0)
Requires-Dist: requests (>=2.28.1)
Requires-Dist: rich (>=12.6.0)
Requires-Dist: toml (>=0.10.2)
Project-URL: Repository, https://github.com/Bernardoow/gl_search
